sampling/__init__.py
sampling/handlers.py
sampling/hdf_sampling.py
sampling/parsers.py
sampling/utils.py
sampling/bin/sst.py
shakemap_sampling_tool-1.0.dist-info/LICENSE.md
shakemap_sampling_tool-1.0.dist-info/METADATA
shakemap_sampling_tool-1.0.dist-info/WHEEL
shakemap_sampling_tool-1.0.dist-info/entry_points.txt
shakemap_sampling_tool-1.0.dist-info/top_level.txt
shakemap_sampling_tool-1.0.dist-info/RECORD
