Metadata-Version: 2.1
Name: shakemap-sampling-tool
Version: 1.0
Summary: USGS Earthquake Basic Geographic Utilities
Author-email: Mike Hearne <mhearne@usgs.gov>
License: License
Keywords: shakemap,sampling
Requires-Python: >=3.9
License-File: LICENSE.md
Requires-Dist: pandas>=2.2.1
Requires-Dist: openpyxl>=3.1.4
Requires-Dist: h5py>=3.11.0
Provides-Extra: dev
Requires-Dist: build>=0.7.0; extra == "dev"
Requires-Dist: black>=21; extra == "dev"
Requires-Dist: flake8>=3.9; extra == "dev"
Requires-Dist: ipython>=7.26; extra == "dev"
Requires-Dist: twine>=4.0.2; extra == "dev"
Provides-Extra: test
Requires-Dist: pytest>=6.2; extra == "test"
Requires-Dist: pytest-cov>=2.12.0; extra == "test"
Provides-Extra: build
Requires-Dist: build; extra == "build"
Requires-Dist: twine; extra == "build"
Requires-Dist: check-wheel-contents; extra == "build"
